pyrule_compendium/__init__.py
pyrule_compendium/defaults.py
pyrule_compendium/exceptions.py
pyrule_compendium/objects.py
pyrule_compendium/utils.py
pyrule_compendium-2.4.1.dist-info/LICENSE
pyrule_compendium-2.4.1.dist-info/METADATA
pyrule_compendium-2.4.1.dist-info/WHEEL
pyrule_compendium-2.4.1.dist-info/top_level.txt
pyrule_compendium-2.4.1.dist-info/RECORD
